setup.py
lookout/__init__.py
lookout/github.py
lookout/sourceforge.py
lookout.egg-info/PKG-INFO
lookout.egg-info/SOURCES.txt
lookout.egg-info/dependency_links.txt
lookout.egg-info/requires.txt
lookout.egg-info/top_level.txt