Metadata-Version: 1.1
Name: lookout
Version: 0.0.1
Summary: API for scanning for new releases of libraries and programs.
Home-page: https://github.com/madebr/lookout
Author: Anonymous Maarten
Author-email: anonymous.maarten@gmail.com
License: GPLv3+
Platform: UNKNOWN
Classifier: Topic :: System :: Software Distribution
Classifier: Intended Audience :: Developers
Classifier: License :: OSI Approved :: GNU General Public License v3 or later (GPLv3+)
Classifier: Programming Language :: Python :: 3 :: Only  
Classifier: Topic :: Software Development
Classifier: Development Status :: 1 - Planning
